{"http://rdfs.org/ns/void#linkPredicate": ["http://xmlns.com/foaf/0.1/primaryTopic"], "http://rdfs.org/ns/void#objectsTarget": ["http://openstreetmap.org/node/"], "http://rdfs.org/ns/void#subjectsTarget": ["http://research-squirrel-engineers.github.io/osm2lod/osm2lod"], "http://rdfs.org/ns/void#triples": ["105", "2", "9", "686"], "http://www.w3.org/1999/02/22-rdf-syntax-ns#type": ["http://rdfs.org/ns/void#Linkset", "http://www.w3.org/ns/ldp#Resource", "https://www.iana.org/assignments/media-types/text/turtle#Resource"], "http://www.w3.org/2000/01/rdf-schema#label": ["Linkset: osm2lod - node"]}