{"http://ldf.fi/void-ext#averageLiteralLength": ["24", "21", "22", "23"], "http://ldf.fi/void-ext#averageObjectIRILength": ["58", "55", "56"], "http://ldf.fi/void-ext#averagePropertyIRILength": ["56", "50", "52", "57"], "http://ldf.fi/void-ext#averageSubjectIRILength": ["68", "69", "70"], "http://ldf.fi/void-ext#datatypes": ["2"], "http://ldf.fi/void-ext#distinctBlankNodes": ["0"], "http://ldf.fi/void-ext#distinctIRIReferences": ["986", "94", "145", "5328"], "http://ldf.fi/void-ext#distinctLiterals": ["452", "33", "64", "2298"], "http://ldf.fi/void-ext#distinctRDFNodes": ["1438", "127", "209", "7626"], "http://ldf.fi/void-ext#languages": ["3", "1", "4", "6"], "http://ldf.fi/void-ext#propertyClasses": ["0"], "http://purl.org/dc/elements/1.1/language": ["http://www.lexvo.org/page/iso639-1/en"], "http://purl.org/dc/terms/modified": ["2025-12-19T12:07:55"], "http://purl.org/dc/terms/subject": ["http://www.wikidata.org/entity/Q121810372", "http://xmlns.com/foaf/0.1/Person", "http://dbpedia.org/resource/Location", "http://dbpedia.org/resource/OGC_GeoSPARQL", "http://dbpedia.org/resource/Time"], "http://purl.org/dc/terms/title": ["osm2lod"], "http://purl.org/vocab/vann/preferredNamespacePrefix": ["osm2lod"], "http://purl.org/vocab/vann/preferredNamespaceUri": ["http://research-squirrel-engineers.github.io/osm2lod/"], "http://rdfs.org/ns/void#classPartition": ["http://research-squirrel-engineers.github.io/osm2lod/osm2lod_Point", "http://research-squirrel-engineers.github.io/osm2lod/osm2lod_E22_Human_Made_Object", "http://research-squirrel-engineers.github.io/osm2lod/osm2lod_Catalog", "http://research-squirrel-engineers.github.io/osm2lod/osm2lod_FeatureCollection", "http://research-squirrel-engineers.github.io/osm2lod/osm2lod_Collection", "http://research-squirrel-engineers.github.io/osm2lod/osm2lod_OSMEntity", "http://research-squirrel-engineers.github.io/osm2lod/osm2lod_Dataset", "http://research-squirrel-engineers.github.io/osm2lod/osm2lod_SpatialObjectCollection", "http://research-squirrel-engineers.github.io/osm2lod/osm2lod_GeometryCollection", "http://research-squirrel-engineers.github.io/osm2lod/osm2lod_E26_Physical_Feature", "http://research-squirrel-engineers.github.io/osm2lod/osm2lod_E55_Place"], "http://rdfs.org/ns/void#classes": ["10"], "http://rdfs.org/ns/void#dataDump": ["https://Research-Squirrel-Engineers.github.io/osm2lod//index.ttl"], "http://rdfs.org/ns/void#distinctObjects": ["732", "50", "93", "3859"], "http://rdfs.org/ns/void#distinctSubjects": ["221", "19", "27", "1433"], "http://rdfs.org/ns/void#entities": ["218", "16", "24", "1430"], "http://rdfs.org/ns/void#feature": ["http://www.w3.org/ns/formats/Turtle", "http://www.w3.org/ns/formats/RDFa"], "http://rdfs.org/ns/void#properties": ["33", "25", "36"], "http://rdfs.org/ns/void#propertyPartition": ["http://research-squirrel-engineers.github.io/osm2lod/osm2lod_osmtag__url", "http://research-squirrel-engineers.github.io/osm2lod/osm2lod_osmtag__description", "http://research-squirrel-engineers.github.io/osm2lod/osm2lod_identifier", "http://research-squirrel-engineers.github.io/osm2lod/osm2lod_exportType", "http://research-squirrel-engineers.github.io/osm2lod/osm2lod_osmtag__name", "http://research-squirrel-engineers.github.io/osm2lod/osm2lod_osmtag__image", "http://research-squirrel-engineers.github.io/osm2lod/osm2lod_osmtag__website", "http://research-squirrel-engineers.github.io/osm2lod/osm2lod_osmtag__source", "http://research-squirrel-engineers.github.io/osm2lod/osm2lod_osmtag__wikimedia_commons", "http://research-squirrel-engineers.github.io/osm2lod/osm2lod_osmtag__source__ref", "http://research-squirrel-engineers.github.io/osm2lod/osm2lod_provenance", "http://research-squirrel-engineers.github.io/osm2lod/osm2lod_title", "http://research-squirrel-engineers.github.io/osm2lod/osm2lod_osmtag__historic__civilization", "http://research-squirrel-engineers.github.io/osm2lod/osm2lod_isPartOf", "http://research-squirrel-engineers.github.io/osm2lod/osm2lod_osmtag__ref", "http://research-squirrel-engineers.github.io/osm2lod/osm2lod_osmtag__tourism", "http://research-squirrel-engineers.github.io/osm2lod/osm2lod_asWKT", "http://research-squirrel-engineers.github.io/osm2lod/osm2lod_rights", "http://research-squirrel-engineers.github.io/osm2lod/osm2lod_osmtag__wikidata", "http://research-squirrel-engineers.github.io/osm2lod/osm2lod_label", "http://research-squirrel-engineers.github.io/osm2lod/osm2lod_osmtag__loc_name", "http://research-squirrel-engineers.github.io/osm2lod/osm2lod_hasGeometry", "http://research-squirrel-engineers.github.io/osm2lod/osm2lod_osmtag__archaeological_site", "http://research-squirrel-engineers.github.io/osm2lod/osm2lod_osmtag__historic", "http://research-squirrel-engineers.github.io/osm2lod/osm2lod_sameAs", "http://research-squirrel-engineers.github.io/osm2lod/osm2lod_osmtag__access", "http://research-squirrel-engineers.github.io/osm2lod/osm2lod_created", "http://research-squirrel-engineers.github.io/osm2lod/osm2lod_osmtag__alt_name", "http://research-squirrel-engineers.github.io/osm2lod/osm2lod_osmtag__note", "http://research-squirrel-engineers.github.io/osm2lod/osm2lod_osmtag__wikipedia", "http://research-squirrel-engineers.github.io/osm2lod/osm2lod_primaryTopic", "http://research-squirrel-engineers.github.io/osm2lod/osm2lod_type", "http://research-squirrel-engineers.github.io/osm2lod/osm2lod_osmtag__denomination", "http://research-squirrel-engineers.github.io/osm2lod/osm2lod_osmtag__ele", "http://research-squirrel-engineers.github.io/osm2lod/osm2lod_osmtag__int_name", "http://research-squirrel-engineers.github.io/osm2lod/osm2lod_osmtag__man_made", "http://research-squirrel-engineers.github.io/osm2lod/osm2lod_osmtag__natural", "http://research-squirrel-engineers.github.io/osm2lod/osm2lod_osmtag__operator", "http://research-squirrel-engineers.github.io/osm2lod/osm2lod_osmtag__place_of_worship", "http://research-squirrel-engineers.github.io/osm2lod/osm2lod_osmtag__religion", "http://research-squirrel-engineers.github.io/osm2lod/osm2lod_osmtag__source__url", "http://research-squirrel-engineers.github.io/osm2lod/osm2lod_osmtag__volcano__status", "http://research-squirrel-engineers.github.io/osm2lod/osm2lod_osmtag__volcano__type", "http://research-squirrel-engineers.github.io/osm2lod/osm2lod_osmtag__water", "http://research-squirrel-engineers.github.io/osm2lod/osm2lod_osmtag__water_source", "http://research-squirrel-engineers.github.io/osm2lod/osm2lod_source"], "http://rdfs.org/ns/void#triples": ["2367", "156", "245", "16428"], "http://rdfs.org/ns/void#uriSpace": ["http://research-squirrel-engineers.github.io/osm2lod/"], "http://rdfs.org/ns/void#vocabulary": ["http://www.w3.org/ns/adms#", "http://www.w3.org/ns/prov#", "http://www.w3.org/2006/time#", "http://purl.org/dc/terms/", "http://purl.org/vocab/vann/", "http://www.w3.org/1999/02/22-rdf-syntax-ns#", "http://rdfs.org/ns/void#", "http://www.w3.org/ns/csvw#", "http://usefulinc.com/ns/doap#", "http://www.w3.org/2004/02/skos/core#", "http://www.w3.org/ns/ssn/", "http://www.w3.org/ns/sosa/", "https://brickschema.org/schema/Brick#", "https://www.w3.org/2003/01/geo/wgs84_pos#", "http://www.w3.org/ns/shacl#", "http://purl.org/vocommons/voaf#", "http://www.w3.org/ns/dcat#", "http://purl.org/dc/dcmitype/", "http://www.w3.org/XML/1998/namespace", "http://www.w3.org/2000/01/rdf-schema#", "http://www.w3.org/ns/odrl/2/", "http://xmlns.com/foaf/0.1/", "http://www.w3.org/2001/XMLSchema#", "http://purl.org/dc/elements/1.1/", "http://www.opengis.net/ont/geosparql#", "http://www.w3.org/ns/org#", "http://purl.org/dc/dcam/", "http://www.w3.org/ns/dx/prof/", "https://schema.org/", "http://purl.org/linked-data/cube#", "http://ldf.fi/void-ext#", "http://www.w3.org/2002/07/owl#"], "http://www.w3.org/1999/02/22-rdf-syntax-ns#type": ["http://www.w3.org/ns/adms#Asset", "http://rdfs.org/ns/void#Dataset", "http://www.w3.org/ns/ldp#Resource", "https://www.iana.org/assignments/media-types/text/turtle#Resource"], "http://www.w3.org/2000/01/rdf-schema#label": ["osm2lod"], "http://www.w3.org/ns/dcat#distribution": ["http://research-squirrel-engineers.github.io/osm2lod/osm2lod_dist_ttl"], "http://www.w3.org/ns/dcat#keyword": ["Time", "Location", "Q121810372", "OGC GeoSPARQL", "Person"], "http://www.w3.org/ns/dcat#landingPage": ["https://Research-Squirrel-Engineers.github.io/osm2lod/"], "http://xmlns.com/foaf/0.1/homepage": ["https://Research-Squirrel-Engineers.github.io/osm2lod/"], "http://xmlns.com/foaf/0.1/page": ["https://Research-Squirrel-Engineers.github.io/osm2lod//index.html"]}